hampel.py
hampel-0.0.5.dist-info/LICENSE
hampel-0.0.5.dist-info/METADATA
hampel-0.0.5.dist-info/WHEEL
hampel-0.0.5.dist-info/top_level.txt
hampel-0.0.5.dist-info/RECORD
