Metadata-Version: 2.1
Name: hampel
Version: 0.0.5
Summary: Python implementation of the Hampel Filter
Home-page: https://github.com/MichaelisTrofficus/hampel_filter
Author: MTrofficus
Author-email: miguel.otero.pedrido.1993@gmail.com
License: UNKNOWN
Platform: UNKNOWN
Classifier: Programming Language :: Python :: 3
Classifier: License :: OSI Approved :: MIT License
Classifier: Operating System :: OS Independent
Requires-Python: >=3.5
Requires-Dist: numpy
Requires-Dist: pandas
